[
  {
    "category": [
      {
        "category": [],
        "alias": "smog_check_stations",
        "title": "Abgasuntersuchung"
      },
      {
        "category": [],
        "alias": "towing",
        "title": "Abschleppdienste"
      },
      {
        "category": [],
        "alias": "autopartssupplies",
        "title": "Auto-Ersatzteile"
      },
      {
        "category": [],
        "alias": "autorepair",
        "title": "Auto-Reparaturen"
      },
      {
        "category": [],
        "alias": "car_dealers",
        "title": "Autohändler"
      },
      {
        "category": [],
        "alias": "tires",
        "title": "Autoreifen"
      },
      {
        "category": [],
        "alias": "carwash",
        "title": "Autowaschanlagen"
      },
      {
        "category": [],
        "alias": "motorcycledealers",
        "title": "Motorradhändler"
      },
      {
        "category": [],
        "alias": "motorcyclerepair",
        "title": "Motorradreparatur"
      },
      {
        "category": [],
        "alias": "parking",
        "title": "Parkplätze"
      },
      {
        "category": [],
        "alias": "servicestations",
        "title": "Tankstellen & Autowerkstätten"
      }
    ],
    "alias": "auto",
    "title": "Auto"
  },
  {
    "category": [
      {
        "category": [],
        "alias": "barbers",
        "title": "Barbiere"
      },
      {
        "category": [],
        "alias": "hair",
        "title": "Coiffeure"
      },
      {
        "category": [],
        "alias": "spas",
        "title": "Day Spas"
      },
      {
        "category": [
          {
            "category": [],
            "alias": "laser_hair_removal",
            "title": "Laser-Haarentfernung"
          }
        ],
        "alias": "hairremoval",
        "title": "Haarentfernung"
      },
      {
        "category": [],
        "alias": "skincare",
        "title": "Haut- & Körperpflege"
      },
      {
        "category": [],
        "alias": "cosmetics",
        "title": "Kosmetik- und Schönheitsartikel"
      },
      {
        "category": [],
        "alias": "medicalspa",
        "title": "Kurmittelhäuser"
      },
      {
        "category": [],
        "alias": "massage",
        "title": "Massage"
      },
      {
        "category": [],
        "alias": "othersalons",
        "title": "Nagelstudios"
      },
      {
        "category": [],
        "alias": "perfume",
        "title": "Parfümerien"
      },
      {
        "category": [],
        "alias": "piercing",
        "title": "Piercing"
      },
      {
        "category": [],
        "alias": "tanning",
        "title": "Solarien & Sonnenbänke"
      },
      {
        "category": [],
        "alias": "tattoo",
        "title": "Tätowierungen"
      },
      {
        "category": [],
        "alias": "makeupartists",
        "title": "Visagisten"
      },
      {
        "category": [],
        "alias": "eyelashservice",
        "title": "Wimpernstudio"
      }
    ],
    "alias": "beautysvc",
    "title": "Beauty & Wellness"
  },
  {
    "category": [
      {
        "category": [],
        "alias": "adultedu",
        "title": "Erwachsenenbildung"
      },
      {
        "category": [],
        "alias": "elementaryschools",
        "title": "Grundschulen"
      },
      {
        "category": [],
        "alias": "collegeuniv",
        "title": "Hochschulen & Universitäten"
      },
      {
        "category": [],
        "alias": "preschools",
        "title": "Kindergärten"
      },
      {
        "category": [],
        "alias": "privatetutors",
        "title": "Nachhilfelehrer"
      },
      {
        "category": [],
        "alias": "tutoring",
        "title": "Nachhilfezentren"
      },
      {
        "category": [],
        "alias": "testprep",
        "title": "Prüfungsvorbereitung"
      },
      {
        "category": [],
        "alias": "specialed",
        "title": "Sonderpädagogik"
      },
      {
        "category": [
          {
            "category": [],
            "alias": "vocation",
            "title": "Berufsschulen"
          },
          {
            "category": [],
            "alias": "driving_schools",
            "title": "Fahrschulen"
          },
          {
            "category": [],
            "alias": "flightinstruction",
            "title": "Flugunterricht"
          },
          {
            "category": [],
            "alias": "cookingschools",
            "title": "Kochkurse & Kochschulen"
          },
          {
            "category": [],
            "alias": "cosmetology_schools",
            "title": "Kosmetikschulen"
          },
          {
            "category": [],
            "alias": "artschools",
            "title": "Kunstakademien"
          },
          {
            "category": [],
            "alias": "massage_schools",
            "title": "Massageschulen"
          },
          {
            "category": [],
            "alias": "swimminglessons",
            "title": "Schwimmunterricht"
          },
          {
            "category": [],
            "alias": "language_schools",
            "title": "Sprachschulen & Sprachunterricht"
          },
          {
            "category": [],
            "alias": "dance_schools",
            "title": "Tanzschulen"
          }
        ],
        "alias": "specialtyschools",
        "title": "Spezialisierte Schulen"
      },
      {
        "category": [],
        "alias": "educationservices",
        "title": "Weiterbildung"
      },
      {
        "category": [],
        "alias": "highschools",
        "title": "Weiterführende Schulen"
      }
    ],
    "alias": "education",
    "title": "Bildung"
  },
  {
    "category": [
      {
        "category": [],
        "alias": "advertising",
        "title": "Anzeigen"
      },
      {
        "category": [],
        "alias": "employmentagencies",
        "title": "Arbeitsvermittlungen"
      },
      {
        "category": [],
        "alias": "architects",
        "title": "Architekten"
      },
      {
        "category": [],
        "alias": "careercounseling",
        "title": "Berufsberatung"
      },
      {
        "category": [],
        "alias": "accountants",
        "title": "Buchhalter "
      },
      {
        "category": [],
        "alias": "officecleaning",
        "title": "Büroreinigung"
      },
      {
        "category": [],
        "alias": "graphicdesign",
        "title": "Grafikdesign"
      },
      {
        "category": [],
        "alias": "isps",
        "title": "Internetservice"
      },
      {
        "category": [],
        "alias": "lifecoach",
        "title": "Life-Coaching"
      },
      {
        "category": [],
        "alias": "marketing",
        "title": "Marketing"
      },
      {
        "category": [],
        "alias": "privateinvestigation",
        "title": "Privatdetektive"
      },
      {
        "category": [
          {
            "category": [],
            "alias": "general_litigation",
            "title": "Allgemeine Rechtsstreitigkeiten"
          },
          {
            "category": [],
            "alias": "employmentlawyers",
            "title": "Arbeitsrecht"
          },
          {
            "category": [],
            "alias": "immigrationlawyers",
            "title": "Einwanderungsrecht & Ausländerrecht"
          },
          {
            "category": [],
            "alias": "realestatelawyers",
            "title": "Immobilienrecht"
          },
          {
            "category": [],
            "alias": "bankruptcy",
            "title": "Insolvenzrecht"
          },
          {
            "category": [],
            "alias": "estateplanning",
            "title": "Nachlassplanung"
          },
          {
            "category": [],
            "alias": "personal_injury",
            "title": "Personenschäden & Schadenersatz"
          },
          {
            "category": [],
            "alias": "divorce",
            "title": "Scheidungs- & Familienrecht"
          },
          {
            "category": [],
            "alias": "criminaldefense",
            "title": "Strafverteidigung"
          }
        ],
        "alias": "lawyers",
        "title": "Rechtsanwälte"
      },
      {
        "category": [],
        "alias": "boatrepair",
        "title": "Schiffsreparatur"
      },
      {
        "category": [],
        "alias": "security",
        "title": "Security Services"
      },
      {
        "category": [],
        "alias": "videofilmproductions",
        "title": "Video-/Filmproduktion"
      },
      {
        "category": [],
        "alias": "web_design",
        "title": "Webdesign"
      },
      {
        "category": [],
        "alias": "publicrelations",
        "title": "Öffentlichkeitsarbeit & PR"
      }
    ],
    "alias": "professional",
    "title": "Dienstleistungen"
  },
  {
    "category": [
      {
        "category": [],
        "alias": "boatcharters",
        "title": "Bootsverleih"
      },
      {
        "category": [],
        "alias": "catering",
        "title": "Cateringservice"
      },
      {
        "category": [],
        "alias": "djs",
        "title": "DJs"
      },
      {
        "category": [],
        "alias": "photographers",
        "title": "Fotografen"
      },
      {
        "category": [],
        "alias": "wedding_planning",
        "title": "Hochzeitsplanung"
      },
      {
        "category": [],
        "alias": "hotels",
        "title": "Hotels"
      },
      {
        "category": [],
        "alias": "stationery",
        "title": "Papeterie"
      },
      {
        "category": [],
        "alias": "eventplanning",
        "title": "Party- & Eventplanung"
      },
      {
        "category": [],
        "alias": "partysupplies",
        "title": "Partybedarf"
      },
      {
        "category": [],
        "alias": "personalchefs",
        "title": "Privat-Köche"
      },
      {
        "category": [],
        "alias": "venues",
        "title": "Tagungs- & Veranstaltungsorte"
      },
      {
        "category": [],
        "alias": "videographers",
        "title": "Videographie"
      }
    ],
    "alias": "eventservices",
    "title": "Eventplanung & -Service"
  },
  {
    "category": [
      {
        "category": [],
        "alias": "banks",
        "title": "Banken"
      },
      {
        "category": [],
        "alias": "financialadvising",
        "title": "Finanzberatung"
      },
      {
        "category": [],
        "alias": "investing",
        "title": "Investitionen"
      },
      {
        "category": [],
        "alias": "taxservices",
        "title": "Steuerberater"
      },
      {
        "category": [],
        "alias": "insurance",
        "title": "Versicherungen"
      }
    ],
    "alias": "financialservices",
    "title": "Finanzdienstleistungen"
  },
  {
    "category": [
      {
        "category": [],
        "alias": "acupuncture",
        "title": "Akupunktur"
      },
      {
        "category": [],
        "alias": "pharmacy",
        "title": "Apotheken"
      },
      {
        "category": [],
        "alias": "optometrists",
        "title": "Augenoptiker"
      },
      {
        "category": [],
        "alias": "chiropractors",
        "title": "Chiropraktiker"
      },
      {
        "category": [],
        "alias": "weightlosscenters",
        "title": "Diätzentren"
      },
      {
        "category": [],
        "alias": "nutritionists",
        "title": "Ernährungsberater"
      },
      {
        "category": [],
        "alias": "medcenters",
        "title": "Gesundheitszentren"
      },
      {
        "category": [],
        "alias": "midwives",
        "title": "Hebammen"
      },
      {
        "category": [],
        "alias": "medicalspa",
        "title": "Kurmittelhäuser"
      },
      {
        "category": [],
        "alias": "laserlasikeyes",
        "title": "Laser-Augenoperationen"
      },
      {
        "category": [],
        "alias": "speech_therapists",
        "title": "Logopäden"
      },
      {
        "category": [],
        "alias": "urgent_care",
        "title": "Notdienste & Notaufnahmen"
      },
      {
        "category": [],
        "alias": "homehealthcare",
        "title": "Pflegedienste"
      },
      {
        "category": [],
        "alias": "hospice",
        "title": "Pflegeheim"
      },
      {
        "category": [],
        "alias": "physicaltherapy",
        "title": "Physiotherapie"
      },
      {
        "category": [],
        "alias": "c_and_mh",
        "title": "Psychologische Beratung"
      },
      {
        "category": [],
        "alias": "saunas",
        "title": "Saunas"
      },
      {
        "category": [],
        "alias": "retirement_homes",
        "title": "Seniorenheime"
      },
      {
        "category": [],
        "alias": "hospitals",
        "title": "Spitäler"
      },
      {
        "category": [],
        "alias": "tcm",
        "title": "Traditionelle Chinesische Medizin"
      },
      {
        "category": [
          {
            "category": [],
            "alias": "generaldentistry",
            "title": "Allgemeine Zahnheilkunde"
          },
          {
            "category": [],
            "alias": "endodontists",
            "title": "Endodontisten"
          },
          {
            "category": [],
            "alias": "oralsurgeons",
            "title": "Kieferchirurgen"
          },
          {
            "category": [],
            "alias": "orthodontists",
            "title": "Kieferorthopäden"
          },
          {
            "category": [],
            "alias": "pediatric_dentists",
            "title": "Kinderzahnärzte"
          },
          {
            "category": [],
            "alias": "cosmeticdentists",
            "title": "Kosmetische Zahnärzte"
          },
          {
            "category": [],
            "alias": "periodontists",
            "title": "Parodontologen"
          }
        ],
        "alias": "dentists",
        "title": "Zahnärzte"
      },
      {
        "category": [
          {
            "category": [],
            "alias": "allergist",
            "title": "Allergologen"
          },
          {
            "category": [],
            "alias": "familydr",
            "title": "Allgemeinmediziner"
          },
          {
            "category": [],
            "alias": "audiologist",
            "title": "Audiologen"
          },
          {
            "category": [],
            "alias": "opthamalogists",
            "title": "Augenärzte"
          },
          {
            "category": [],
            "alias": "surgeons",
            "title": "Chirurgen"
          },
          {
            "category": [],
            "alias": "dermatology",
            "title": "Dermatologen"
          },
          {
            "category": [],
            "alias": "tattooremoval",
            "title": "Entfernung von Tätowierungen"
          },
          {
            "category": [],
            "alias": "obgyn",
            "title": "Frauenärzte"
          },
          {
            "category": [],
            "alias": "fertility",
            "title": "Fruchtbarkeit"
          },
          {
            "category": [],
            "alias": "gastroenterologist",
            "title": "Gastroenterologen"
          },
          {
            "category": [],
            "alias": "gerontologist",
            "title": "Gerontologen"
          },
          {
            "category": [],
            "alias": "earnosethroat",
            "title": "Hals-, Nasen- & Ohrenärzte"
          },
          {
            "category": [],
            "alias": "internalmed",
            "title": "Internisten"
          },
          {
            "category": [],
            "alias": "cardiology",
            "title": "Kardiologen"
          },
          {
            "category": [],
            "alias": "pediatricians",
            "title": "Kinderärzte"
          },
          {
            "category": [],
            "alias": "cosmeticsurgeons",
            "title": "Kosmetische Chirurgen"
          },
          {
            "category": [],
            "alias": "naturopathic",
            "title": "Naturheilkunde"
          },
          {
            "category": [],
            "alias": "neurologist",
            "title": "Neurologe"
          },
          {
            "category": [],
            "alias": "oncologist",
            "title": "Onkologe"
          },
          {
            "category": [],
            "alias": "orthopedists",
            "title": "Orthopäden"
          },
          {
            "category": [],
            "alias": "osteopathicphysicians",
            "title": "Osteopathen"
          },
          {
            "category": [],
            "alias": "podiatrists",
            "title": "Podologe"
          },
          {
            "category": [],
            "alias": "proctologist",
            "title": "Proktologen"
          },
          {
            "category": [],
            "alias": "psychiatrists",
            "title": "Psychiater"
          },
          {
            "category": [],
            "alias": "pulmonologist",
            "title": "Pulmonologist"
          },
          {
            "category": [],
            "alias": "sportsmed",
            "title": "Sportmedizin"
          }
        ],
        "alias": "physicians",
        "title": "Ärzte"
      }
    ],
    "alias": "health",
    "title": "Gesundheit & Ärzte"
  },
  {
    "category": [
      {
        "category": [],
        "alias": "treeservices",
        "title": "Baumpflege"
      },
      {
        "category": [],
        "alias": "buildingsupplies",
        "title": "Baumärkte"
      },
      {
        "category": [],
        "alias": "contractors",
        "title": "Bauunternehmen"
      },
      {
        "category": [],
        "alias": "lighting",
        "title": "Beleuchtung"
      },
      {
        "category": [],
        "alias": "roofing",
        "title": "Dachdecker"
      },
      {
        "category": [],
        "alias": "electricians",
        "title": "Elektriker"
      },
      {
        "category": [],
        "alias": "windowsinstallation",
        "title": "Fensterinstallationen"
      },
      {
        "category": [],
        "alias": "windowwashing",
        "title": "Fensterreinigung"
      },
      {
        "category": [],
        "alias": "televisionserviceproviders",
        "title": "Fernsehanbieter"
      },
      {
        "category": [],
        "alias": "flooring",
        "title": "Fussbodenbeläge"
      },
      {
        "category": [],
        "alias": "gardeners",
        "title": "Gärtner"
      },
      {
        "category": [],
        "alias": "handyman",
        "title": "Handwerker"
      },
      {
        "category": [],
        "alias": "hometheatreinstallation",
        "title": "Heimkinoinstallation"
      },
      {
        "category": [],
        "alias": "hvac",
        "title": "Heizung & Klimaanlagen"
      },
      {
        "category": [
          {
            "category": [],
            "alias": "propertymgmt",
            "title": "Hausverwaltung"
          },
          {
            "category": [],
            "alias": "mortgagebrokers",
            "title": "Hypothekenmakler"
          },
          {
            "category": [],
            "alias": "realestateagents",
            "title": "Makler"
          },
          {
            "category": [],
            "alias": "university_housing",
            "title": "Studentenwohnheime"
          },
          {
            "category": [],
            "alias": "apartments",
            "title": "Wohnungen"
          }
        ],
        "alias": "realestate",
        "title": "Immobilien- & Wohnungsmarkt"
      },
      {
        "category": [],
        "alias": "home_inspectors",
        "title": "Immobiliensachverständige"
      },
      {
        "category": [],
        "alias": "interiordesign",
        "title": "Inneneinrichtung"
      },
      {
        "category": [],
        "alias": "isps",
        "title": "Internetservice"
      },
      {
        "category": [],
        "alias": "blinds",
        "title": "Jalousien & Vorhänge"
      },
      {
        "category": [],
        "alias": "landscapearchitects",
        "title": "Landschaftsarchitekten"
      },
      {
        "category": [],
        "alias": "landscaping",
        "title": "Landschaftsbau"
      },
      {
        "category": [],
        "alias": "painters",
        "title": "Maler & Tapezierer"
      },
      {
        "category": [],
        "alias": "homecleaning",
        "title": "Reinigungskräfte"
      },
      {
        "category": [],
        "alias": "plumbing",
        "title": "Sanitär"
      },
      {
        "category": [],
        "alias": "locksmiths",
        "title": "Schlüsseldienste"
      },
      {
        "category": [],
        "alias": "carpenters",
        "title": "Schreiner"
      },
      {
        "category": [],
        "alias": "poolcleaners",
        "title": "Schwimmbadreinigung"
      },
      {
        "category": [],
        "alias": "securitysystems",
        "title": "Sicherheitssysteme"
      },
      {
        "category": [],
        "alias": "solarinstallation",
        "title": "Solarinstallationen"
      },
      {
        "category": [],
        "alias": "carpeting",
        "title": "Teppichböden"
      },
      {
        "category": [],
        "alias": "carpetinstallation",
        "title": "Teppichverleger"
      },
      {
        "category": [],
        "alias": "movers",
        "title": "Umzugsunternehmen"
      }
    ],
    "alias": "homeservices",
    "title": "Handwerksleistungen"
  },
  {
    "category": [
      {
        "category": [],
        "alias": "petstore",
        "title": "Haustierbedarf"
      },
      {
        "category": [
          {
            "category": [],
            "alias": "dogwalkers",
            "title": "Dogwalker"
          },
          {
            "category": [],
            "alias": "pet_sitting",
            "title": "Haustierbetreuung"
          },
          {
            "category": [],
            "alias": "groomer",
            "title": "Hunde- & Katzensalon"
          },
          {
            "category": [],
            "alias": "pet_training",
            "title": "Hundeschulen"
          }
        ],
        "alias": "petservices",
        "title": "Haustierservices"
      },
      {
        "category": [],
        "alias": "animalshelters",
        "title": "Tierheime"
      },
      {
        "category": [],
        "alias": "vet",
        "title": "Tierärzte"
      }
    ],
    "alias": "pets",
    "title": "Haustiere"
  },
  {
    "category": [
      {
        "category": [],
        "alias": "propertymgmt",
        "title": "Hausverwaltung"
      },
      {
        "category": [],
        "alias": "mortgagebrokers",
        "title": "Hypothekenmakler"
      },
      {
        "category": [],
        "alias": "realestateagents",
        "title": "Makler"
      },
      {
        "category": [],
        "alias": "university_housing",
        "title": "Studentenwohnheime"
      },
      {
        "category": [],
        "alias": "apartments",
        "title": "Wohnungen"
      }
    ],
    "alias": "realestate",
    "title": "Immobilien- & Wohnungsmarkt"
  },
  {
    "category": [
      {
        "category": [],
        "alias": "gardens",
        "title": "Botanische Gärten"
      },
      {
        "category": [],
        "alias": "jazzandblues",
        "title": "Jazz & Blues"
      },
      {
        "category": [],
        "alias": "casinos",
        "title": "Kasinos"
      },
      {
        "category": [],
        "alias": "movietheaters",
        "title": "Kinos"
      },
      {
        "category": [],
        "alias": "galleries",
        "title": "Kunstgalerien"
      },
      {
        "category": [
          {
            "category": [],
            "alias": "funfair",
            "title": "Chilbi"
          },
          {
            "category": [],
            "alias": "generalfestivals",
            "title": "Festivals"
          },
          {
            "category": [],
            "alias": "tradefairs",
            "title": "Messen"
          },
          {
            "category": [],
            "alias": "xmasmarkets",
            "title": "Weihnachtsmärkte"
          }
        ],
        "alias": "festivals",
        "title": "Messen & Festivals"
      },
      {
        "category": [],
        "alias": "museums",
        "title": "Museen"
      },
      {
        "category": [],
        "alias": "opera",
        "title": "Oper & Ballett"
      },
      {
        "category": [],
        "alias": "sportsteams",
        "title": "Professionelle Sportmannschaften"
      },
      {
        "category": [],
        "alias": "arcades",
        "title": "Spielhallen"
      },
      {
        "category": [],
        "alias": "stadiumsarenas",
        "title": "Stadien & Arenen"
      },
      {
        "category": [],
        "alias": "theater",
        "title": "Theater & Performance"
      },
      {
        "category": [],
        "alias": "musicvenues",
        "title": "Veranstaltungsorte"
      },
      {
        "category": [],
        "alias": "social_clubs",
        "title": "Vereine"
      },
      {
        "category": [],
        "alias": "psychic_astrology",
        "title": "Wahrsager & Astrologen"
      },
      {
        "category": [],
        "alias": "wineries",
        "title": "Weinhandlungen & Winzer"
      }
    ],
    "alias": "arts",
    "title": "Kunst & Entertainment"
  },
  {
    "category": [
      {
        "category": [],
        "alias": "junkremovalandhauling",
        "title": "Abfallentsorgung"
      },
      {
        "category": [],
        "alias": "recording_studios",
        "title": "Aufnahme- & Proberäume"
      },
      {
        "category": [],
        "alias": "itservices",
        "title": "Computerreparaturen"
      },
      {
        "category": [],
        "alias": "copyshops",
        "title": "Copyshops & Druckereien "
      },
      {
        "category": [],
        "alias": "electronicsrepair",
        "title": "Elektroinstallationen"
      },
      {
        "category": [],
        "alias": "funeralservices",
        "title": "Friedhöfe & Beerdigungsinstitute"
      },
      {
        "category": [],
        "alias": "nonprofit",
        "title": "Gemeinnützige Verbände"
      },
      {
        "category": [],
        "alias": "homeappliancerepair",
        "title": "Haushaltsgeräte"
      },
      {
        "category": [],
        "alias": "pest_control",
        "title": "Kammerjäger"
      },
      {
        "category": [],
        "alias": "childcare",
        "title": "Kinderbetreuung"
      },
      {
        "category": [],
        "alias": "couriers",
        "title": "Kurierdienste"
      },
      {
        "category": [],
        "alias": "selfstorage",
        "title": "Lagerräume & Storage"
      },
      {
        "category": [],
        "alias": "shipping_centers",
        "title": "Logistik- & Versandzentren"
      },
      {
        "category": [],
        "alias": "notaries",
        "title": "Notare & Urkundenbeglaubigungen"
      },
      {
        "category": [],
        "alias": "reupholstery",
        "title": "Polstereien"
      },
      {
        "category": [],
        "alias": "record_labels",
        "title": "Record Labels"
      },
      {
        "category": [],
        "alias": "recyclingcenter",
        "title": "Recycling-Centers"
      },
      {
        "category": [],
        "alias": "snowremoval",
        "title": "Schneeräumung"
      },
      {
        "category": [],
        "alias": "shoerepair",
        "title": "Schuhmacher"
      },
      {
        "category": [],
        "alias": "screenprinting",
        "title": "Siebdruck"
      },
      {
        "category": [],
        "alias": "carpet_cleaning",
        "title": "Teppichreinigung"
      },
      {
        "category": [],
        "alias": "watch_repair",
        "title": "Uhrmacher"
      },
      {
        "category": [],
        "alias": "drycleaninglaundry",
        "title": "Wäschereien & Reinigungen"
      },
      {
        "category": [],
        "alias": "sewingalterations",
        "title": "Änderungsschneidereien"
      }
    ],
    "alias": "localservices",
    "title": "Lokale Dienstleistungen"
  },
  {
    "category": [],
    "alias": "localflavor",
    "title": "Lokales"
  },
  {
    "category": [
      {
        "category": [],
        "alias": "televisionstations",
        "title": "Fernsehsender"
      },
      {
        "category": [],
        "alias": "printmedia",
        "title": "Printmedien"
      },
      {
        "category": [],
        "alias": "radiostations",
        "title": "Radiosender"
      }
    ],
    "alias": "massmedia",
    "title": "Medien"
  },
  {
    "category": [
      {
        "category": [
          {
            "category": [],
            "alias": "beachbars",
            "title": "Beachbars"
          },
          {
            "category": [],
            "alias": "champagne_bars",
            "title": "Champagnerbars"
          },
          {
            "category": [],
            "alias": "cocktailbars",
            "title": "Cocktailbars"
          },
          {
            "category": [],
            "alias": "gaybars",
            "title": "Gay & Lesbian"
          },
          {
            "category": [],
            "alias": "irish_pubs",
            "title": "Irish Pub"
          },
          {
            "category": [],
            "alias": "divebars",
            "title": "Kneipen"
          },
          {
            "category": [],
            "alias": "lounges",
            "title": "Lounges"
          },
          {
            "category": [],
            "alias": "pubs",
            "title": "Pubs"
          },
          {
            "category": [],
            "alias": "hookah_bars",
            "title": "Shisha-Bars"
          },
          {
            "category": [],
            "alias": "wine_bars",
            "title": "Weinbars"
          }
        ],
        "alias": "bars",
        "title": "Bars"
      },
      {
        "category": [],
        "alias": "poolhalls",
        "title": "Billardsalons"
      },
      {
        "category": [],
        "alias": "comedyclubs",
        "title": "Comedy-Clubs"
      },
      {
        "category": [],
        "alias": "danceclubs",
        "title": "Diskotheken & Clubs"
      },
      {
        "category": [],
        "alias": "adultentertainment",
        "title": "Erotik"
      },
      {
        "category": [],
        "alias": "jazzandblues",
        "title": "Jazz & Blues"
      },
      {
        "category": [],
        "alias": "karaoke",
        "title": "Karaoke"
      },
      {
        "category": [],
        "alias": "musicvenues",
        "title": "Veranstaltungsorte"
      }
    ],
    "alias": "nightlife",
    "title": "Nightlife"
  },
  {
    "category": [
      {
        "category": [],
        "alias": "tours",
        "title": "Ausflüge & Touren"
      },
      {
        "category": [],
        "alias": "carrental",
        "title": "Autovermietung"
      },
      {
        "category": [],
        "alias": "trainstations",
        "title": "Bahnhöfe"
      },
      {
        "category": [],
        "alias": "bedbreakfast",
        "title": "Bed & Breakfast"
      },
      {
        "category": [],
        "alias": "campgrounds",
        "title": "Campingplätze"
      },
      {
        "category": [],
        "alias": "vacationrentalagents",
        "title": "Ferienhausvermietung"
      },
      {
        "category": [],
        "alias": "airports",
        "title": "Flughäfen"
      },
      {
        "category": [],
        "alias": "guesthouses",
        "title": "Gästehäuser"
      },
      {
        "category": [],
        "alias": "hotels",
        "title": "Hotels"
      },
      {
        "category": [],
        "alias": "hostels",
        "title": "Jugendherbergen"
      },
      {
        "category": [],
        "alias": "travelservices",
        "title": "Reisebüros"
      },
      {
        "category": [],
        "alias": "skiresorts",
        "title": "Skigebiete"
      },
      {
        "category": [
          {
            "category": [],
            "alias": "airlines",
            "title": "Fluggesellschaften"
          },
          {
            "category": [],
            "alias": "airport_shuttles",
            "title": "Flughafen-Shuttle"
          },
          {
            "category": [],
            "alias": "limos",
            "title": "Limousinen"
          },
          {
            "category": [],
            "alias": "taxis",
            "title": "Taxis"
          },
          {
            "category": [],
            "alias": "publictransport",
            "title": "Öffentliche Verkehrsmittel"
          }
        ],
        "alias": "transport",
        "title": "Transport & Beförderung"
      },
      {
        "category": [],
        "alias": "rvrental",
        "title": "Wohnmobilvermietung"
      }
    ],
    "alias": "hotelstravel",
    "title": "Reisen & Tourismus"
  },
  {
    "category": [
      {
        "category": [],
        "alias": "buddhist_temples",
        "title": "Buddhistische Tempel"
      },
      {
        "category": [],
        "alias": "hindu_temples",
        "title": "Hinduistische Tempel"
      },
      {
        "category": [],
        "alias": "churches",
        "title": "Kirchen"
      },
      {
        "category": [],
        "alias": "mosques",
        "title": "Moscheen"
      },
      {
        "category": [],
        "alias": "synagogues",
        "title": "Synagogen"
      }
    ],
    "alias": "religiousorgs",
    "title": "Religiöse Einrichtungen"
  },
  {
    "category": [
      {
        "category": [],
        "alias": "afghani",
        "title": "Afghanisch"
      },
      {
        "category": [],
        "alias": "african",
        "title": "Afrikanisch"
      },
      {
        "category": [],
        "alias": "diners",
        "title": "American Diner"
      },
      {
        "category": [],
        "alias": "tradamerican",
        "title": "Amerikanisch"
      },
      {
        "category": [],
        "alias": "arabian",
        "title": "Arabisch"
      },
      {
        "category": [],
        "alias": "argentine",
        "title": "Argentinisch"
      },
      {
        "category": [],
        "alias": "asianfusion",
        "title": "Asiatisch"
      },
      {
        "category": [],
        "alias": "australian",
        "title": "Australisch"
      },
      {
        "category": [],
        "alias": "bbq",
        "title": "Barbecue"
      },
      {
        "category": [],
        "alias": "basque",
        "title": "Baskisch"
      },
      {
        "category": [],
        "alias": "bavarian",
        "title": "Bayrisch"
      },
      {
        "category": [],
        "alias": "belgian",
        "title": "Belgisch"
      },
      {
        "category": [],
        "alias": "beergarden",
        "title": "Biergärten"
      },
      {
        "category": [],
        "alias": "beerhall",
        "title": "Bierhalle"
      },
      {
        "category": [],
        "alias": "bistros",
        "title": "Bistros"
      },
      {
        "category": [],
        "alias": "brazilian",
        "title": "Brasilianisch"
      },
      {
        "category": [],
        "alias": "brasseries",
        "title": "Brasserien"
      },
      {
        "category": [],
        "alias": "british",
        "title": "Britisch"
      },
      {
        "category": [],
        "alias": "buffets",
        "title": "Buffets"
      },
      {
        "category": [],
        "alias": "bulgarian",
        "title": "Bulgarisch"
      },
      {
        "category": [],
        "alias": "burgers",
        "title": "Burger"
      },
      {
        "category": [],
        "alias": "burmese",
        "title": "Burmesisch"
      },
      {
        "category": [],
        "alias": "cafes",
        "title": "Cafés"
      },
      {
        "category": [
          {
            "category": [],
            "alias": "dimsum",
            "title": "Dim Sum"
          }
        ],
        "alias": "chinese",
        "title": "Chinesisch"
      },
      {
        "category": [],
        "alias": "creperies",
        "title": "Crêpes"
      },
      {
        "category": [],
        "alias": "currysausage",
        "title": "Currywurst"
      },
      {
        "category": [],
        "alias": "german",
        "title": "Deutsch"
      },
      {
        "category": [],
        "alias": "kebab",
        "title": "Döner"
      },
      {
        "category": [],
        "alias": "eltern_cafes",
        "title": "Elterncafé"
      },
      {
        "category": [],
        "alias": "hotdogs",
        "title": "Fastfood & Take Away"
      },
      {
        "category": [],
        "alias": "seafood",
        "title": "Fisch & Meeresfrüchte"
      },
      {
        "category": [],
        "alias": "fishnchips",
        "title": "Fish & Chips"
      },
      {
        "category": [],
        "alias": "fondue",
        "title": "Fondue"
      },
      {
        "category": [],
        "alias": "french",
        "title": "Französisch"
      },
      {
        "category": [],
        "alias": "breakfast_brunch",
        "title": "Frühstück & Brunch"
      },
      {
        "category": [],
        "alias": "gluten_free",
        "title": "Glutenfrei"
      },
      {
        "category": [],
        "alias": "greek",
        "title": "Griechisch"
      },
      {
        "category": [],
        "alias": "halal",
        "title": "Halal"
      },
      {
        "category": [],
        "alias": "hawaiian",
        "title": "Hawaiisch"
      },
      {
        "category": [],
        "alias": "hotdog",
        "title": "Hotdogs"
      },
      {
        "category": [],
        "alias": "foodstands",
        "title": "Imbissbuden"
      },
      {
        "category": [],
        "alias": "indpak",
        "title": "Indisch"
      },
      {
        "category": [],
        "alias": "indonesian",
        "title": "Indonesisch"
      },
      {
        "category": [],
        "alias": "international",
        "title": "International"
      },
      {
        "category": [],
        "alias": "irish",
        "title": "Irisch"
      },
      {
        "category": [],
        "alias": "israeli",
        "title": "Israelisch"
      },
      {
        "category": [],
        "alias": "italian",
        "title": "Italienisch"
      },
      {
        "category": [],
        "alias": "japanese",
        "title": "Japanisch"
      },
      {
        "category": [],
        "alias": "cambodian",
        "title": "Kambodschanisch"
      },
      {
        "category": [],
        "alias": "caribbean",
        "title": "Karibisch"
      },
      {
        "category": [],
        "alias": "tapas",
        "title": "Kleine Gerichte"
      },
      {
        "category": [],
        "alias": "korean",
        "title": "Koreanisch"
      },
      {
        "category": [],
        "alias": "kosher",
        "title": "Kosher"
      },
      {
        "category": [],
        "alias": "cajun",
        "title": "Kreolisch & Cajun"
      },
      {
        "category": [],
        "alias": "cuban",
        "title": "Kubanisch"
      },
      {
        "category": [],
        "alias": "latin",
        "title": "Lateinamerikanisch"
      },
      {
        "category": [],
        "alias": "lebanese",
        "title": "Libanesisch"
      },
      {
        "category": [],
        "alias": "malaysian",
        "title": "Malaysisch"
      },
      {
        "category": [],
        "alias": "moroccan",
        "title": "Marokkanisch"
      },
      {
        "category": [],
        "alias": "mediterranean",
        "title": "Mediterran"
      },
      {
        "category": [],
        "alias": "canteen",
        "title": "Mensa / Kantine"
      },
      {
        "category": [],
        "alias": "mexican",
        "title": "Mexikanisch"
      },
      {
        "category": [],
        "alias": "modern_european",
        "title": "Modern-Europäisch"
      },
      {
        "category": [],
        "alias": "mongolian",
        "title": "Mongolisch"
      },
      {
        "category": [],
        "alias": "mideastern",
        "title": "Naher Osten"
      },
      {
        "category": [],
        "alias": "himalayan",
        "title": "Nepalesisch"
      },
      {
        "category": [],
        "alias": "oriental",
        "title": "Orientalisch"
      },
      {
        "category": [],
        "alias": "pakistani",
        "title": "Pakistanisch"
      },
      {
        "category": [],
        "alias": "persian",
        "title": "Persisch/Iranisch"
      },
      {
        "category": [],
        "alias": "peruvian",
        "title": "Peruanisch"
      },
      {
        "category": [],
        "alias": "filipino",
        "title": "Philippinisch"
      },
      {
        "category": [],
        "alias": "pizza",
        "title": "Pizza"
      },
      {
        "category": [],
        "alias": "polish",
        "title": "Polnisch"
      },
      {
        "category": [],
        "alias": "portuguese",
        "title": "Portugiesisch"
      },
      {
        "category": [],
        "alias": "raw_food",
        "title": "Rohkost"
      },
      {
        "category": [],
        "alias": "rumanian",
        "title": "Rumänisch"
      },
      {
        "category": [],
        "alias": "russian",
        "title": "Russisch"
      },
      {
        "category": [],
        "alias": "salad",
        "title": "Salat"
      },
      {
        "category": [],
        "alias": "sandwiches",
        "title": "Sandwiches"
      },
      {
        "category": [],
        "alias": "scottish",
        "title": "Schottisch"
      },
      {
        "category": [],
        "alias": "swissfood",
        "title": "Schweizer Küche "
      },
      {
        "category": [],
        "alias": "swabian",
        "title": "Schwäbisch"
      },
      {
        "category": [],
        "alias": "serbocroatian",
        "title": "Serbo-Kroatisch"
      },
      {
        "category": [],
        "alias": "singaporean",
        "title": "Singapurisch"
      },
      {
        "category": [],
        "alias": "scandinavian",
        "title": "Skandinavisch"
      },
      {
        "category": [],
        "alias": "spanish",
        "title": "Spanisch"
      },
      {
        "category": [],
        "alias": "steak",
        "title": "Steakhäuser"
      },
      {
        "category": [],
        "alias": "soup",
        "title": "Suppen & Eintöpfe"
      },
      {
        "category": [],
        "alias": "sushi",
        "title": "Sushi-Bars"
      },
      {
        "category": [],
        "alias": "taiwanese",
        "title": "Taiwanesisch"
      },
      {
        "category": [],
        "alias": "tapasmallplates",
        "title": "Tapas/kleine Gerichte"
      },
      {
        "category": [],
        "alias": "tex-mex",
        "title": "Tex-Mex"
      },
      {
        "category": [],
        "alias": "thai",
        "title": "Thailändisch"
      },
      {
        "category": [],
        "alias": "turkish",
        "title": "Türkisch"
      },
      {
        "category": [],
        "alias": "ukrainian",
        "title": "Ukrainisch"
      },
      {
        "category": [],
        "alias": "hungarian",
        "title": "Ungarisch"
      },
      {
        "category": [],
        "alias": "vegan",
        "title": "Vegan"
      },
      {
        "category": [],
        "alias": "vegetarian",
        "title": "Vegetarisch"
      },
      {
        "category": [],
        "alias": "vietnamese",
        "title": "Vietnamesisch"
      },
      {
        "category": [],
        "alias": "gastropubs",
        "title": "Wirtschaften"
      },
      {
        "category": [],
        "alias": "cypriot",
        "title": "Zypriotisch"
      },
      {
        "category": [],
        "alias": "ethiopian",
        "title": "Äthiopisch"
      },
      {
        "category": [],
        "alias": "austrian",
        "title": "Österreichisch"
      }
    ],
    "alias": "restaurants",
    "title": "Restaurants"
  },
  {
    "category": [
      {
        "category": [],
        "alias": "usedbooks",
        "title": "Antiquariat"
      },
      {
        "category": [],
        "alias": "antiques",
        "title": "Antiquitäten"
      },
      {
        "category": [],
        "alias": "baby_gear",
        "title": "Babyausstattungen"
      },
      {
        "category": [
          {
            "category": [],
            "alias": "florists",
            "title": "Floristen & Blumenläden"
          },
          {
            "category": [],
            "alias": "stationery",
            "title": "Papeterie"
          }
        ],
        "alias": "flowers",
        "title": "Blumen & Geschenke"
      },
      {
        "category": [],
        "alias": "bridal",
        "title": "Brautmoden"
      },
      {
        "category": [],
        "alias": "opticians",
        "title": "Brillen & Optiker"
      },
      {
        "category": [],
        "alias": "thrift_stores",
        "title": "Brocki"
      },
      {
        "category": [
          {
            "category": [],
            "alias": "bookstores",
            "title": "Buchhandlungen"
          },
          {
            "category": [],
            "alias": "comicbooks",
            "title": "Comics"
          },
          {
            "category": [],
            "alias": "musicvideo",
            "title": "Musik & DVDs'"
          },
          {
            "category": [],
            "alias": "vinyl_records",
            "title": "Schallplatten"
          },
          {
            "category": [],
            "alias": "videoandgames",
            "title": "Videotheken"
          },
          {
            "category": [],
            "alias": "mags",
            "title": "Zeitungen & Zeitschriften"
          }
        ],
        "alias": "media",
        "title": "Bücher, Magazine, Musik & Video"
      },
      {
        "category": [],
        "alias": "officeequipment",
        "title": "Büroausstattung"
      },
      {
        "category": [],
        "alias": "computers",
        "title": "Computer"
      },
      {
        "category": [],
        "alias": "discountstore",
        "title": "Discounter"
      },
      {
        "category": [],
        "alias": "drugstores",
        "title": "Drogerien"
      },
      {
        "category": [],
        "alias": "shoppingcenters",
        "title": "Einkaufszentren"
      },
      {
        "category": [],
        "alias": "electronics",
        "title": "Elektronik"
      },
      {
        "category": [],
        "alias": "wholesale_stores",
        "title": "En gros"
      },
      {
        "category": [],
        "alias": "fleamarkets",
        "title": "Flohmärkte"
      },
      {
        "category": [],
        "alias": "photographystores",
        "title": "Fotoläden"
      },
      {
        "category": [],
        "alias": "knittingsupplies",
        "title": "Handarbeitsläden"
      },
      {
        "category": [],
        "alias": "mobilephones",
        "title": "Handys"
      },
      {
        "category": [
          {
            "category": [],
            "alias": "hardware",
            "title": "Computerzubehör"
          },
          {
            "category": [],
            "alias": "gardening",
            "title": "Gärtnereien & Baumschulen"
          },
          {
            "category": [],
            "alias": "appliances",
            "title": "Haushaltsgeräte"
          },
          {
            "category": [],
            "alias": "homedecor",
            "title": "Inneneinrichtungen"
          },
          {
            "category": [],
            "alias": "kitchenandbath",
            "title": "Küche & Bad"
          },
          {
            "category": [],
            "alias": "mattresses",
            "title": "Matratzen"
          },
          {
            "category": [],
            "alias": "furniture",
            "title": "Möbelgeschäfte & Einrichtungshäuser"
          },
          {
            "category": [],
            "alias": "hottubandpool",
            "title": "Whirlpools & Swimmingpools"
          }
        ],
        "alias": "homeandgarden",
        "title": "Haus & Garten"
      },
      {
        "category": [],
        "alias": "hobbyshops",
        "title": "Hobbybedarf"
      },
      {
        "category": [],
        "alias": "kiosk",
        "title": "Kiosk"
      },
      {
        "category": [],
        "alias": "cosmetics",
        "title": "Kosmetik- und Schönheitsartikel"
      },
      {
        "category": [],
        "alias": "galleries",
        "title": "Kunstgalerien"
      },
      {
        "category": [
          {
            "category": [],
            "alias": "framing",
            "title": "Einrahmungen"
          },
          {
            "category": [],
            "alias": "costumes",
            "title": "Kostüme & Verkleidungen"
          },
          {
            "category": [],
            "alias": "artsupplies",
            "title": "Künstlerbedarf"
          },
          {
            "category": [],
            "alias": "stationery",
            "title": "Papeterie"
          },
          {
            "category": [],
            "alias": "fabricstores",
            "title": "Textilien & Stoffe"
          }
        ],
        "alias": "artsandcrafts",
        "title": "Kunsthandwerk"
      },
      {
        "category": [
          {
            "category": [],
            "alias": "accessories",
            "title": "Accessoires"
          },
          {
            "category": [],
            "alias": "swimwear",
            "title": "Badebekleidung"
          },
          {
            "category": [],
            "alias": "womenscloth",
            "title": "Damenbekleidung"
          },
          {
            "category": [],
            "alias": "lingerie",
            "title": "Dessous"
          },
          {
            "category": [],
            "alias": "menscloth",
            "title": "Herrenbekleidung"
          },
          {
            "category": [],
            "alias": "childcloth",
            "title": "Kinderbekleidung"
          },
          {
            "category": [],
            "alias": "leather",
            "title": "Lederwaren"
          },
          {
            "category": [],
            "alias": "shoes",
            "title": "Schuhläden"
          },
          {
            "category": [],
            "alias": "vintage",
            "title": "Secondhand-Läden"
          },
          {
            "category": [],
            "alias": "sportswear",
            "title": "Sportbekleidung"
          },
          {
            "category": [],
            "alias": "maternity",
            "title": "Umstandsmode"
          },
          {
            "category": [],
            "alias": "deptstores",
            "title": "Warenhäuser"
          }
        ],
        "alias": "fashion",
        "title": "Mode"
      },
      {
        "category": [],
        "alias": "musicalinstrumentsandteachers",
        "title": "Musikläden & Musiklehrer"
      },
      {
        "category": [],
        "alias": "outlet_stores",
        "title": "Outlets"
      },
      {
        "category": [],
        "alias": "perfume",
        "title": "Parfümerien"
      },
      {
        "category": [],
        "alias": "personal_shopping",
        "title": "Personal Shopping"
      },
      {
        "category": [],
        "alias": "pawn",
        "title": "Pfandleiher"
      },
      {
        "category": [],
        "alias": "jewelry",
        "title": "Schmuck & Accessoires"
      },
      {
        "category": [],
        "alias": "adult",
        "title": "Sexshops und Erotik"
      },
      {
        "category": [],
        "alias": "souvenirs",
        "title": "Souvenirs & Kitsch"
      },
      {
        "category": [],
        "alias": "toys",
        "title": "Spielwarenläden"
      },
      {
        "category": [
          {
            "category": [],
            "alias": "outdoorgear",
            "title": "Outdoor"
          },
          {
            "category": [],
            "alias": "sportswear",
            "title": "Sportbekleidung"
          },
          {
            "category": [],
            "alias": "bikes",
            "title": "Velohandler & Velomech"
          }
        ],
        "alias": "sportgoods",
        "title": "Sportausrüstung"
      },
      {
        "category": [],
        "alias": "tobaccoshops",
        "title": "Tabakläden"
      },
      {
        "category": [],
        "alias": "luggage",
        "title": "Taschen & Koffer"
      },
      {
        "category": [],
        "alias": "tickets",
        "title": "Tickets"
      },
      {
        "category": [],
        "alias": "watches",
        "title": "Uhren"
      },
      {
        "category": [],
        "alias": "deptstores",
        "title": "Warenhäuser"
      }
    ],
    "alias": "shopping",
    "title": "Shopping"
  },
  {
    "category": [
      {
        "category": [],
        "alias": "registry_office",
        "title": "Bezirksgericht"
      },
      {
        "category": [],
        "alias": "libraries",
        "title": "Bibliotheken"
      },
      {
        "category": [],
        "alias": "embassy",
        "title": "Konsulate & Botschaften"
      },
      {
        "category": [],
        "alias": "policedepartments",
        "title": "Polizei"
      },
      {
        "category": [],
        "alias": "postoffices",
        "title": "Postämter"
      },
      {
        "category": [],
        "alias": "landmarks",
        "title": "Sehenswürdigkeiten"
      },
      {
        "category": [],
        "alias": "departmentsofmotorvehicles",
        "title": "Strassenverkehrsamt"
      }
    ],
    "alias": "publicservicesgovt",
    "title": "Sightseeing & Behörden"
  },
  {
    "category": [
      {
        "category": [],
        "alias": "bagels",
        "title": "Bagels"
      },
      {
        "category": [],
        "alias": "beer_and_wine",
        "title": "Bier, Wein & Schnaps"
      },
      {
        "category": [],
        "alias": "organic_stores",
        "title": "Bio- & Naturkostläden"
      },
      {
        "category": [],
        "alias": "breweries",
        "title": "Brauereien"
      },
      {
        "category": [],
        "alias": "bakeries",
        "title": "Bäckereien"
      },
      {
        "category": [],
        "alias": "desserts",
        "title": "Desserts & Süsspeisen"
      },
      {
        "category": [],
        "alias": "donuts",
        "title": "Donuts"
      },
      {
        "category": [],
        "alias": "eltern_cafes",
        "title": "Elterncafé"
      },
      {
        "category": [],
        "alias": "fooddeliveryservices",
        "title": "Essenlieferservice"
      },
      {
        "category": [],
        "alias": "delicatessen",
        "title": "Feinkost & Delikatessen"
      },
      {
        "category": [],
        "alias": "beverage_stores",
        "title": "Getränkehandel"
      },
      {
        "category": [],
        "alias": "icecream",
        "title": "Glacé & Sorbet"
      },
      {
        "category": [],
        "alias": "internetcafe",
        "title": "Internet Cafés"
      },
      {
        "category": [],
        "alias": "coffee",
        "title": "Kaffee & Teeläden"
      },
      {
        "category": [],
        "alias": "kiosk",
        "title": "Kiosk"
      },
      {
        "category": [
          {
            "category": [],
            "alias": "healthmarkets",
            "title": "Bioläden & Reformhäuser"
          },
          {
            "category": [],
            "alias": "seafoodmarkets",
            "title": "Fisch & Meeresfrüchte"
          },
          {
            "category": [],
            "alias": "chocolate",
            "title": "Konfiserien"
          },
          {
            "category": [],
            "alias": "herbsandspices",
            "title": "Kräuter und Gewürze"
          },
          {
            "category": [],
            "alias": "cheese",
            "title": "Käsefachgeschäfte"
          },
          {
            "category": [],
            "alias": "meats",
            "title": "Metzgereien & Fleischereien"
          }
        ],
        "alias": "gourmet",
        "title": "Kulinarische Spezialitäten"
      },
      {
        "category": [],
        "alias": "butcher",
        "title": "Metzger"
      },
      {
        "category": [],
        "alias": "farmersmarket",
        "title": "Märkte"
      },
      {
        "category": [],
        "alias": "convenience",
        "title": "Quartierladen"
      },
      {
        "category": [],
        "alias": "juicebars",
        "title": "Saftbars & Smoothies"
      },
      {
        "category": [],
        "alias": "streetvendors",
        "title": "Strassenhändler"
      },
      {
        "category": [],
        "alias": "grocery",
        "title": "Supermärkte"
      },
      {
        "category": [],
        "alias": "tea",
        "title": "Teestuben"
      },
      {
        "category": [],
        "alias": "wineries",
        "title": "Weinhandlungen & Winzer"
      }
    ],
    "alias": "food",
    "title": "Speis'  & Trank"
  },
  {
    "category": [
      {
        "category": [],
        "alias": "amateursportsteams",
        "title": "Amateur-Vereine"
      },
      {
        "category": [],
        "alias": "fishing",
        "title": "Angeln"
      },
      {
        "category": [],
        "alias": "aquariums",
        "title": "Aquarien"
      },
      {
        "category": [],
        "alias": "hot_air_balloons",
        "title": "Ballonfahren"
      },
      {
        "category": [],
        "alias": "archery",
        "title": "Bogenschiessen"
      },
      {
        "category": [],
        "alias": "boating",
        "title": "Bootfahren"
      },
      {
        "category": [],
        "alias": "bowling",
        "title": "Bowling & Kegeln"
      },
      {
        "category": [],
        "alias": "skatingrinks",
        "title": "Eisbahnen"
      },
      {
        "category": [],
        "alias": "skydiving",
        "title": "Fallschirmspringen"
      },
      {
        "category": [],
        "alias": "summer_camps",
        "title": "Ferienlager"
      },
      {
        "category": [
          {
            "category": [],
            "alias": "gyms",
            "title": "Fitnessstudios"
          },
          {
            "category": [],
            "alias": "martialarts",
            "title": "Kampfsportarten"
          },
          {
            "category": [],
            "alias": "healthtrainers",
            "title": "Personal Trainer"
          },
          {
            "category": [],
            "alias": "pilates",
            "title": "Pilates"
          },
          {
            "category": [],
            "alias": "swimminglessons",
            "title": "Schwimmunterricht"
          },
          {
            "category": [],
            "alias": "taichi",
            "title": "Tai Chi"
          },
          {
            "category": [],
            "alias": "dancestudio",
            "title": "Tanzstudios"
          },
          {
            "category": [],
            "alias": "yoga",
            "title": "Yoga"
          }
        ],
        "alias": "fitness",
        "title": "Fitness"
      },
      {
        "category": [],
        "alias": "recreation",
        "title": "Freizeitzentren"
      },
      {
        "category": [],
        "alias": "discgolf",
        "title": "Frisbee & Discgolf"
      },
      {
        "category": [],
        "alias": "football",
        "title": "Fussball"
      },
      {
        "category": [],
        "alias": "gokarts",
        "title": "Gokartbahnen"
      },
      {
        "category": [],
        "alias": "golf",
        "title": "Golfplätze"
      },
      {
        "category": [],
        "alias": "kids_activities",
        "title": "Kinderaktivitäten"
      },
      {
        "category": [],
        "alias": "climbing",
        "title": "Klettern"
      },
      {
        "category": [],
        "alias": "mini_golf",
        "title": "Minigolf"
      },
      {
        "category": [],
        "alias": "mountainbiking",
        "title": "Mountain Biking"
      },
      {
        "category": [
          {
            "category": [],
            "alias": "dog_parks",
            "title": "Hundeparks"
          },
          {
            "category": [],
            "alias": "skate_parks",
            "title": "Skateparks"
          }
        ],
        "alias": "parks",
        "title": "Parks & Grünanlagen"
      },
      {
        "category": [],
        "alias": "horseracing",
        "title": "Pferderennen"
      },
      {
        "category": [],
        "alias": "rafting",
        "title": "Rafting / Kajakfahren"
      },
      {
        "category": [],
        "alias": "horsebackriding",
        "title": "Reiten & Reithallen"
      },
      {
        "category": [],
        "alias": "swimmingpools",
        "title": "Schwimmbäder & Badis"
      },
      {
        "category": [],
        "alias": "lakes",
        "title": "Seen"
      },
      {
        "category": [],
        "alias": "gliding",
        "title": "Segelfliegen"
      },
      {
        "category": [],
        "alias": "sailing",
        "title": "Segeln"
      },
      {
        "category": [],
        "alias": "skiing",
        "title": "Skifahren & Schlitteln"
      },
      {
        "category": [],
        "alias": "playgrounds",
        "title": "Spielplätze"
      },
      {
        "category": [],
        "alias": "leisure_centers",
        "title": "Sporthallen & -plätze"
      },
      {
        "category": [],
        "alias": "sports_clubs",
        "title": "Sportvereine"
      },
      {
        "category": [],
        "alias": "beaches",
        "title": "Strände"
      },
      {
        "category": [
          {
            "category": [],
            "alias": "freediving",
            "title": "Freitauchen"
          },
          {
            "category": [],
            "alias": "scuba",
            "title": "Tauchen"
          }
        ],
        "alias": "diving",
        "title": "Tauchen"
      },
      {
        "category": [],
        "alias": "tennis",
        "title": "Tennis"
      },
      {
        "category": [],
        "alias": "bikerentals",
        "title": "Velos & Veloverleih"
      },
      {
        "category": [],
        "alias": "amusementparks",
        "title": "Vergnügungsparks"
      },
      {
        "category": [],
        "alias": "hiking",
        "title": "Wandern"
      },
      {
        "category": [],
        "alias": "zoos",
        "title": "Zoos & Freigehege"
      }
    ],
    "alias": "active",
    "title": "Sport & Freizeit"
  }
]
